{"type":"FeatureCollection","features":[{"type":"Feature","properties":{"stopCode":"M1","stopName":"關閘總站","marker-size":"small","marker-color":"#FFC853"},"geometry":{"type":"Point","coordinates":[113.548907,22.214503]}},{"type":"Feature","properties":{"stopCode":"M222","stopName":"看台街","marker-size":"small","marker-color":"#FFC853"},"geometry":{"type":"Point","coordinates":[113.550189,22.213174]}},{"type":"Feature","properties":{"stopCode":"M217","stopName":"看台街/中銀","marker-size":"small","marker-color":"#FFC853"},"geometry":{"type":"Point","coordinates":[113.5514,22.212966]}},{"type":"Feature","properties":{"stopCode":"M220","stopName":"祐漢街市","marker-size":"small","marker-color":"#FFC853"},"geometry":{"type":"Point","coordinates":[113.551962,22.211519]}},{"type":"Feature","properties":{"stopCode":"M221","stopName":"祐漢公園","marker-size":"small","marker-color":"#FFC853"},"geometry":{"type":"Point","coordinates":[113.552628,22.210825]}},{"type":"Feature","properties":{"stopCode":"M224","stopName":"永康街/麗華","marker-size":"small","marker-color":"#FFC853"},"geometry":{"type":"Point","coordinates":[113.551376,22.21]}},{"type":"Feature","properties":{"stopCode":"M215","stopName":"福泰工業大廈","marker-size":"small","marker-color":"#FFC853"},"geometry":{"type":"Point","coordinates":[113.552791,22.209034]}},{"type":"Feature","properties":{"stopCode":"M219","stopName":"勞動節大馬路","marker-size":"small","marker-color":"#FFC853"},"geometry":{"type":"Point","coordinates":[113.555169,22.209717]}},{"type":"Feature","properties":{"stopCode":"M51","stopName":"東北大馬路/廣華","marker-size":"small","marker-color":"#FFC853"},"geometry":{"type":"Point","coordinates":[113.556188,22.207695]}},{"type":"Feature","properties":{"stopCode":"M233","stopName":"東北大馬路/東華","marker-size":"small","marker-color":"#FFC853"},"geometry":{"type":"Point","coordinates":[113.555332,22.206821]}},{"type":"Feature","properties":{"stopCode":"M48","stopName":"慕拉士/飛通大廈","marker-size":"small","marker-color":"#FFC853"},"geometry":{"type":"Point","coordinates":[113.554412,22.20519]}},{"type":"Feature","properties":{"stopCode":"M52","stopName":"漁翁街/勞工事務局","marker-size":"small","marker-color":"#FFC853"},"geometry":{"type":"Point","coordinates":[113.559992,22.204754]}},{"type":"Feature","properties":{"stopCode":"M239","stopName":"外港碼頭","marker-size":"small","marker-color":"#FFC853"},"geometry":{"type":"Point","coordinates":[113.559575,22.198089]}},{"type":"Feature","properties":{"stopCode":"M254","stopName":"友誼馬路/行車天橋","marker-size":"small","marker-color":"#FFC853"},"geometry":{"type":"Point","coordinates":[113.554846,22.194852]}},{"type":"Feature","properties":{"stopCode":"M241","stopName":"旅遊活動中心","marker-size":"small","marker-color":"#FFC853"},"geometry":{"type":"Point","coordinates":[113.553052,22.194683]}},{"type":"Feature","properties":{"stopCode":"M71","stopName":"廈門街/理工","marker-size":"small","marker-color":"#FFC853"},"geometry":{"type":"Point","coordinates":[113.551708,22.193188]}},{"type":"Feature","properties":{"stopCode":"M155","stopName":"東方拱門","marker-size":"small","marker-color":"#FFC853"},"geometry":{"type":"Point","coordinates":[113.549843,22.193858]}},{"type":"Feature","properties":{"stopCode":"M157","stopName":"治安警察局","marker-size":"small","marker-color":"#FFC853"},"geometry":{"type":"Point","coordinates":[113.546628,22.191892]}},{"type":"Feature","properties":{"stopCode":"M169","stopName":"教育暨青年局","marker-size":"small","marker-color":"#FFC853"},"geometry":{"type":"Point","coordinates":[113.543987,22.191863]}},{"type":"Feature","properties":{"stopCode":"M170","stopName":"殷皇子馬路","marker-size":"small","marker-color":"#FFC853"},"geometry":{"type":"Point","coordinates":[113.541707,22.191582]}},{"type":"Feature","properties":{"stopCode":"M172","stopName":"亞馬喇前地","marker-size":"small","marker-color":"#FFC853"},"geometry":{"type":"Point","coordinates":[113.543367,22.189429]}},{"type":"Feature","properties":{"stopCode":"M69","stopName":"葡京酒店","marker-size":"small","marker-color":"#FFC853"},"geometry":{"type":"Point","coordinates":[113.544951,22.18927]}},{"type":"Feature","properties":{"stopCode":"M160","stopName":"十月一日前地","marker-size":"small","marker-color":"#FFC853"},"geometry":{"type":"Point","coordinates":[113.546218,22.190947]}},{"type":"Feature","properties":{"stopCode":"M158","stopName":"北京街/假日酒店","marker-size":"small","marker-color":"#FFC853"},"geometry":{"type":"Point","coordinates":[113.547744,22.191745]}},{"type":"Feature","properties":{"stopCode":"M161","stopName":"高美士/何賢公園","marker-size":"small","marker-color":"#FFC853"},"geometry":{"type":"Point","coordinates":[113.550116,22.192648]}},{"type":"Feature","properties":{"stopCode":"M70","stopName":"理工學院","marker-size":"small","marker-color":"#FFC853"},"geometry":{"type":"Point","coordinates":[113.552025,22.193444]}},{"type":"Feature","properties":{"stopCode":"M118","stopName":"高美士/馬六甲街停車場","marker-size":"small","marker-color":"#FFC853"},"geometry":{"type":"Point","coordinates":[113.553821,22.195763]}},{"type":"Feature","properties":{"stopCode":"M239","stopName":"外港碼頭","marker-size":"small","marker-color":"#FFC853"},"geometry":{"type":"Point","coordinates":[113.559575,22.198089]}},{"type":"Feature","properties":{"stopCode":"M254","stopName":"友誼馬路/行車天橋","marker-size":"small","marker-color":"#FFC853"},"geometry":{"type":"Point","coordinates":[113.554846,22.194852]}},{"type":"Feature","properties":{"stopCode":"M53","stopName":"水塘北角/勞工事務局","marker-size":"small","marker-color":"#FFC853"},"geometry":{"type":"Point","coordinates":[113.559912,22.204693]}},{"type":"Feature","properties":{"stopCode":"M49","stopName":"慕拉士/發電廠","marker-size":"small","marker-color":"#FFC853"},"geometry":{"type":"Point","coordinates":[113.554087,22.205325]}},{"type":"Feature","properties":{"stopCode":"M234","stopName":"東北大馬路/海濱","marker-size":"small","marker-color":"#FFC853"},"geometry":{"type":"Point","coordinates":[113.555225,22.206872]}},{"type":"Feature","properties":{"stopCode":"M206","stopName":"黑沙環新街/海濱","marker-size":"small","marker-color":"#FFC853"},"geometry":{"type":"Point","coordinates":[113.555439,22.207707]}},{"type":"Feature","properties":{"stopCode":"M232","stopName":"黑沙環/政府綜合服務大樓","marker-size":"small","marker-color":"#FFC853"},"geometry":{"type":"Point","coordinates":[113.553306,22.209209]}},{"type":"Feature","properties":{"stopCode":"M246","stopName":"祐漢巿場街","marker-size":"small","marker-color":"#FFC853"},"geometry":{"type":"Point","coordinates":[113.55114,22.210837]}},{"type":"Feature","properties":{"stopCode":"M223","stopName":"長壽馬路","marker-size":"small","marker-color":"#FFC853"},"geometry":{"type":"Point","coordinates":[113.551127,22.212786]}},{"type":"Feature","properties":{"stopCode":"M225","stopName":"看台街/騎士馬路","marker-size":"small","marker-color":"#FFC853"},"geometry":{"type":"Point","coordinates":[113.549406,22.213254]}},{"type":"Feature","properties":{"stopCode":"M8","stopName":"巴波沙大馬路","marker-size":"small","marker-color":"#FFC853"},"geometry":{"type":"Point","coordinates":[113.547594,22.212546]}},{"type":"Feature","properties":{"stopCode":"M1","stopName":"關閘總站","marker-size":"small","marker-color":"#FFC853"},"geometry":{"type":"Point","coordinates":[113.548907,22.214503]}},{"type":"Feature","properties":{"routeCode":"10B","routeName":"關閘 ↻ 南灣"},"geometry":{"type":"LineString","coordinates":[[113.548907,22.214503],[113.549991,22.214351],[113.549846,22.213204],[113.550189,22.213174],[113.551202,22.213026],[113.5514,22.212966],[113.551613,22.212716],[113.551707,22.212433],[113.551578,22.211539],[113.551962,22.211519],[113.552451,22.211401],[113.552598,22.211329],[113.552695,22.211165],[113.552698,22.211021],[113.552628,22.210825],[113.552336,22.210675],[113.55144,22.21081],[113.551376,22.21],[113.551297,22.209729],[113.55112,22.209366],[113.550991,22.208961],[113.552727,22.208345],[113.552791,22.209034],[113.552814,22.209245],[113.553609,22.211002],[113.555169,22.209717],[113.556848,22.208301],[113.556188,22.207695],[113.555332,22.206821],[113.553956,22.205443],[113.554412,22.20519],[113.555422,22.204396],[113.557074,22.204307],[113.559992,22.204754],[113.560294,22.204814],[113.56046,22.205152],[113.56002,22.205787],[113.560246,22.20613],[113.5606,22.206006],[113.560707,22.204635],[113.562268,22.199882],[113.56222,22.199614],[113.560771,22.199162],[113.560069,22.198213],[113.559575,22.198089],[113.557367,22.197435],[113.556713,22.197355],[113.554846,22.194852],[113.554238,22.194099],[113.554248,22.193772],[113.5545,22.193635],[113.554755,22.193916],[113.554487,22.194273],[113.553267,22.195083],[113.553052,22.194683],[113.552132,22.193526],[113.551708,22.193188],[113.550658,22.192855],[113.550133,22.194077],[113.549843,22.193858],[113.546628,22.191892],[113.544548,22.190626],[113.544139,22.190792],[113.544014,22.191202],[113.543987,22.191863],[113.546647,22.189944],[113.546218,22.190947],[113.543453,22.189896],[113.543198,22.189655],[113.543367,22.189429],[113.543444,22.188977],[113.543916,22.188868],[113.544951,22.18927],[113.546647,22.189944],[113.546218,22.190947],[113.546131,22.191097],[113.546135,22.191211],[113.546239,22.191294],[113.546454,22.191394],[113.546548,22.191405],[113.546623,22.191277],[113.547744,22.191745],[113.550116,22.192648],[113.551768,22.19327],[113.552025,22.193444],[113.552185,22.193637],[113.553821,22.195763],[113.553932,22.195988],[113.552971,22.196564],[113.552885,22.196703],[113.553658,22.197607],[113.554507,22.198313],[113.554816,22.198275],[113.556238,22.197414],[113.557257,22.197523],[113.560068,22.198342],[113.560191,22.1988],[113.560384,22.198735],[113.560106,22.198233],[113.559575,22.198089],[113.557367,22.197435],[113.556713,22.197355],[113.554846,22.194852],[113.554258,22.19414],[113.554242,22.193813],[113.554355,22.193661],[113.554628,22.193693],[113.554728,22.193947],[113.554414,22.194394],[113.554414,22.194515],[113.554958,22.195233],[113.555157,22.19534],[113.557289,22.198164],[113.557751,22.198452],[113.561993,22.199687],[113.562144,22.200104],[113.560684,22.204534],[113.560314,22.204723],[113.559912,22.204693],[113.557268,22.204287],[113.55564,22.204247],[113.554087,22.205325],[113.553876,22.205501],[113.555225,22.206872],[113.555734,22.207444],[113.555439,22.207707],[113.553732,22.209107],[113.553306,22.209209],[113.552803,22.209248],[113.55322,22.210168],[113.552326,22.210684],[113.55114,22.210837],[113.550802,22.210884],[113.550973,22.211643],[113.550986,22.211876],[113.551037,22.212033],[113.551127,22.212786],[113.551187,22.213016],[113.551262,22.213637],[113.549924,22.213821],[113.549833,22.213207],[113.549406,22.213254],[113.548741,22.213341],[113.54832,22.211226],[113.548376,22.210977],[113.548349,22.210885],[113.54821,22.210826],[113.547446,22.210836],[113.547594,22.212546],[113.547748,22.214577],[113.547893,22.214667],[113.548907,22.214503]]}}]}
