{"type":"FeatureCollection","features":[{"type":"Feature","properties":{"stopCode":"M1","stopName":"關閘總站","marker-size":"small","marker-color":"#FFC853"},"geometry":{"type":"Point","coordinates":[113.548907,22.214503]}},{"type":"Feature","properties":{"stopCode":"M225","stopName":"看台街/騎士馬路","marker-size":"small","marker-color":"#FFC853"},"geometry":{"type":"Point","coordinates":[113.549406,22.213254]}},{"type":"Feature","properties":{"stopCode":"M7","stopName":"關閘馬路","marker-size":"small","marker-color":"#FFC853"},"geometry":{"type":"Point","coordinates":[113.548544,22.212353]}},{"type":"Feature","properties":{"stopCode":"M16","stopName":"提督馬路/雅廉訪","marker-size":"small","marker-color":"#FFC853"},"geometry":{"type":"Point","coordinates":[113.545304,22.206338]}},{"type":"Feature","properties":{"stopCode":"M98","stopName":"高士德/連勝","marker-size":"small","marker-color":"#FFC853"},"geometry":{"type":"Point","coordinates":[113.545358,22.204464]}},{"type":"Feature","properties":{"stopCode":"M88","stopName":"高士德/賈伯樂","marker-size":"small","marker-color":"#FFC853"},"geometry":{"type":"Point","coordinates":[113.547948,22.202173]}},{"type":"Feature","properties":{"stopCode":"M72","stopName":"陳瑞祺中學","marker-size":"small","marker-color":"#FFC853"},"geometry":{"type":"Point","coordinates":[113.548829,22.198286]}},{"type":"Feature","properties":{"stopCode":"M149","stopName":"粵華中學","marker-size":"small","marker-color":"#FFC853"},"geometry":{"type":"Point","coordinates":[113.547706,22.196995]}},{"type":"Feature","properties":{"stopCode":"M145","stopName":"東望洋新街","marker-size":"small","marker-color":"#FFC853"},"geometry":{"type":"Point","coordinates":[113.545937,22.194625]}},{"type":"Feature","properties":{"stopCode":"M165","stopName":"加思欄花園","marker-size":"small","marker-color":"#FFC853"},"geometry":{"type":"Point","coordinates":[113.545153,22.192693]}},{"type":"Feature","properties":{"stopCode":"M163","stopName":"賈羅布/葡京","marker-size":"small","marker-color":"#FFC853"},"geometry":{"type":"Point","coordinates":[113.545091,22.190456]}},{"type":"Feature","properties":{"stopCode":"M172","stopName":"亞馬喇前地","marker-size":"small","marker-color":"#FFC853"},"geometry":{"type":"Point","coordinates":[113.543367,22.189429]}},{"type":"Feature","properties":{"stopCode":"M69","stopName":"葡京酒店","marker-size":"small","marker-color":"#FFC853"},"geometry":{"type":"Point","coordinates":[113.544951,22.18927]}},{"type":"Feature","properties":{"stopCode":"M160","stopName":"十月一日前地","marker-size":"small","marker-color":"#FFC853"},"geometry":{"type":"Point","coordinates":[113.546218,22.190947]}},{"type":"Feature","properties":{"stopCode":"M158","stopName":"北京街/假日酒店","marker-size":"small","marker-color":"#FFC853"},"geometry":{"type":"Point","coordinates":[113.547744,22.191745]}},{"type":"Feature","properties":{"stopCode":"M161","stopName":"高美士/何賢公園","marker-size":"small","marker-color":"#FFC853"},"geometry":{"type":"Point","coordinates":[113.550116,22.192648]}},{"type":"Feature","properties":{"stopCode":"M70","stopName":"理工學院","marker-size":"small","marker-color":"#FFC853"},"geometry":{"type":"Point","coordinates":[113.552025,22.193444]}},{"type":"Feature","properties":{"stopCode":"M118","stopName":"高美士/馬六甲街停車場","marker-size":"small","marker-color":"#FFC853"},"geometry":{"type":"Point","coordinates":[113.553821,22.195763]}},{"type":"Feature","properties":{"stopCode":"M62","stopName":"回力","marker-size":"small","marker-color":"#FFC853"},"geometry":{"type":"Point","coordinates":[113.555028,22.196638]}},{"type":"Feature","properties":{"stopCode":"M62","stopName":"回力","marker-size":"small","marker-color":"#7F642A"},"geometry":{"type":"Point","coordinates":[113.555028,22.196638]}},{"type":"Feature","properties":{"stopCode":"M117","stopName":"羅理基/馬六甲街","marker-size":"small","marker-color":"#7F642A"},"geometry":{"type":"Point","coordinates":[113.552714,22.196187]}},{"type":"Feature","properties":{"stopCode":"M241","stopName":"旅遊活動中心","marker-size":"small","marker-color":"#7F642A"},"geometry":{"type":"Point","coordinates":[113.553052,22.194683]}},{"type":"Feature","properties":{"stopCode":"M71","stopName":"廈門街/理工","marker-size":"small","marker-color":"#7F642A"},"geometry":{"type":"Point","coordinates":[113.551708,22.193188]}},{"type":"Feature","properties":{"stopCode":"M155","stopName":"東方拱門","marker-size":"small","marker-color":"#7F642A"},"geometry":{"type":"Point","coordinates":[113.549843,22.193858]}},{"type":"Feature","properties":{"stopCode":"M157","stopName":"治安警察局","marker-size":"small","marker-color":"#7F642A"},"geometry":{"type":"Point","coordinates":[113.546628,22.191892]}},{"type":"Feature","properties":{"stopCode":"M163","stopName":"賈羅布/葡京","marker-size":"small","marker-color":"#7F642A"},"geometry":{"type":"Point","coordinates":[113.545091,22.190456]}},{"type":"Feature","properties":{"stopCode":"M164","stopName":"加思欄馬路","marker-size":"small","marker-color":"#7F642A"},"geometry":{"type":"Point","coordinates":[113.544865,22.191074]}},{"type":"Feature","properties":{"stopCode":"M151","stopName":"山頂醫院急診大樓","marker-size":"small","marker-color":"#7F642A"},"geometry":{"type":"Point","coordinates":[113.547446,22.194118]}},{"type":"Feature","properties":{"stopCode":"M150","stopName":"得勝斜巷","marker-size":"small","marker-color":"#7F642A"},"geometry":{"type":"Point","coordinates":[113.548233,22.196071]}},{"type":"Feature","properties":{"stopCode":"M148","stopName":"東望洋斜巷","marker-size":"small","marker-color":"#7F642A"},"geometry":{"type":"Point","coordinates":[113.546498,22.195902]}},{"type":"Feature","properties":{"stopCode":"M76","stopName":"盧廉若公園","marker-size":"small","marker-color":"#7F642A"},"geometry":{"type":"Point","coordinates":[113.548287,22.200179]}},{"type":"Feature","properties":{"stopCode":"M84","stopName":"高士德/培正","marker-size":"small","marker-color":"#7F642A"},"geometry":{"type":"Point","coordinates":[113.54851,22.201497]}},{"type":"Feature","properties":{"stopCode":"M92","stopName":"俾利喇/高士德","marker-size":"small","marker-color":"#7F642A"},"geometry":{"type":"Point","coordinates":[113.547304,22.203206]}},{"type":"Feature","properties":{"stopCode":"M104","stopName":"觀音堂","marker-size":"small","marker-color":"#7F642A"},"geometry":{"type":"Point","coordinates":[113.549761,22.20419]}},{"type":"Feature","properties":{"stopCode":"M43","stopName":"螺絲山公園","marker-size":"small","marker-color":"#7F642A"},"geometry":{"type":"Point","coordinates":[113.551861,22.203151]}},{"type":"Feature","properties":{"stopCode":"M40","stopName":"福海花園","marker-size":"small","marker-color":"#7F642A"},"geometry":{"type":"Point","coordinates":[113.551348,22.205677]}},{"type":"Feature","properties":{"stopCode":"M28","stopName":"黑沙環馬路","marker-size":"small","marker-color":"#7F642A"},"geometry":{"type":"Point","coordinates":[113.549751,22.208122]}},{"type":"Feature","properties":{"stopCode":"M228","stopName":"祐漢第二街","marker-size":"small","marker-color":"#7F642A"},"geometry":{"type":"Point","coordinates":[113.550121,22.210741]}},{"type":"Feature","properties":{"stopCode":"M244","stopName":"中心街","marker-size":"small","marker-color":"#7F642A"},"geometry":{"type":"Point","coordinates":[113.552069,22.21232]}},{"type":"Feature","properties":{"stopCode":"M216","stopName":"馬場東大馬路","marker-size":"small","marker-color":"#7F642A"},"geometry":{"type":"Point","coordinates":[113.553879,22.211811]}},{"type":"Feature","properties":{"stopCode":"M207","stopName":"馬場北大馬路","marker-size":"small","marker-color":"#7F642A"},"geometry":{"type":"Point","coordinates":[113.553085,22.214353]}},{"type":"Feature","properties":{"stopCode":"M1","stopName":"關閘總站","marker-size":"small","marker-color":"#7F642A"},"geometry":{"type":"Point","coordinates":[113.548907,22.214503]}},{"type":"Feature","properties":{"routeCode":"28C","routeName":"關閘 ⇀  回力"},"geometry":{"type":"LineString","coordinates":[[113.548907,22.214503],[113.549996,22.21435],[113.549828,22.213199],[113.549406,22.213254],[113.548738,22.213338],[113.548544,22.212353],[113.548332,22.211247],[113.548374,22.210977],[113.548178,22.210188],[113.547526,22.21024],[113.546351,22.208122],[113.545874,22.207374],[113.545304,22.206338],[113.544886,22.205744],[113.544387,22.205321],[113.545358,22.204464],[113.547948,22.202173],[113.548202,22.201983],[113.549096,22.201127],[113.549224,22.20107],[113.549763,22.20061],[113.550004,22.200353],[113.549747,22.20013],[113.549717,22.199902],[113.550117,22.199517],[113.548829,22.198286],[113.548159,22.197601],[113.547706,22.196995],[113.54679,22.195926],[113.546538,22.195422],[113.546146,22.194811],[113.545937,22.194625],[113.545303,22.193731],[113.544976,22.193147],[113.544992,22.192869],[113.545153,22.192693],[113.545659,22.192129],[113.545133,22.191428],[113.544844,22.190832],[113.545091,22.190456],[113.545179,22.190293],[113.545061,22.190239],[113.544895,22.190574],[113.544656,22.190626],[113.544085,22.190318],[113.543988,22.190286],[113.543439,22.189899],[113.543208,22.189658],[113.543347,22.189496],[113.543367,22.189429],[113.543444,22.188977],[113.543916,22.188868],[113.544951,22.18927],[113.546647,22.189944],[113.546218,22.190947],[113.546131,22.191097],[113.546135,22.191211],[113.546239,22.191294],[113.546454,22.191394],[113.546548,22.191405],[113.546623,22.191277],[113.547744,22.191745],[113.550116,22.192648],[113.551768,22.19327],[113.552025,22.193444],[113.552185,22.193637],[113.553821,22.195763],[113.553942,22.195986],[113.554832,22.195375],[113.555465,22.196279],[113.555436,22.196423],[113.555028,22.196638]]}},{"type":"Feature","properties":{"routeCode":"28C","routeName":"回力 ⇀  關閘"},"geometry":{"type":"LineString","coordinates":[[113.555028,22.196638],[113.555017,22.196701],[113.554913,22.196683],[113.554843,22.19675],[113.554904,22.196862],[113.555028,22.196842],[113.55558,22.197592],[113.555162,22.19788],[113.554905,22.198173],[113.554712,22.198268],[113.554492,22.198228],[113.554368,22.198157],[113.553121,22.196485],[113.552714,22.196187],[113.552303,22.195968],[113.552166,22.195797],[113.553295,22.195114],[113.553052,22.194683],[113.552132,22.193526],[113.551708,22.193188],[113.550658,22.192855],[113.550133,22.194077],[113.549843,22.193858],[113.546628,22.191892],[113.545756,22.191331],[113.544997,22.190812],[113.544932,22.190723],[113.545091,22.190456],[113.545174,22.190296],[113.545056,22.190238],[113.544763,22.190798],[113.544841,22.19084],[113.544865,22.191074],[113.545104,22.191376],[113.545636,22.192131],[113.546628,22.193008],[113.546834,22.193256],[113.547392,22.194081],[113.547446,22.194118],[113.54768,22.194402],[113.548324,22.194715],[113.54855,22.194854],[113.548582,22.194978],[113.548566,22.195333],[113.548721,22.195664],[113.548233,22.196071],[113.547505,22.196795],[113.546772,22.195901],[113.546498,22.195902],[113.545874,22.195943],[113.545013,22.19574],[113.544962,22.195787],[113.544973,22.195899],[113.546367,22.197691],[113.54664,22.197795],[113.547075,22.197706],[113.547423,22.197989],[113.547603,22.198356],[113.547321,22.198749],[113.547313,22.198925],[113.548287,22.200179],[113.548993,22.201077],[113.54851,22.201497],[113.548269,22.201705],[113.548194,22.201827],[113.547531,22.202356],[113.547167,22.202713],[113.546952,22.202857],[113.547161,22.203081],[113.547304,22.203206],[113.548782,22.204992],[113.549761,22.20419],[113.550348,22.203741],[113.550777,22.203356],[113.551539,22.202738],[113.551861,22.203151],[113.552434,22.203841],[113.552102,22.204029],[113.551941,22.204248],[113.551847,22.204639],[113.551603,22.205106],[113.551348,22.205677],[113.551201,22.206033],[113.551048,22.206167],[113.550704,22.206381],[113.550503,22.206535],[113.550278,22.206773],[113.549964,22.207471],[113.549751,22.208122],[113.549574,22.208576],[113.549681,22.208735],[113.549831,22.208762],[113.550051,22.208635],[113.550617,22.209984],[113.550054,22.210177],[113.550121,22.210741],[113.550186,22.210967],[113.55031,22.211732],[113.550978,22.211641],[113.551088,22.212415],[113.551693,22.212327],[113.552069,22.21232],[113.552373,22.212214],[113.552923,22.212182],[113.552971,22.211911],[113.553097,22.211568],[113.553269,22.211308],[113.553376,22.211193],[113.553531,22.211174],[113.55369,22.21119],[113.553879,22.211811],[113.554544,22.213489],[113.554437,22.213837],[113.553085,22.214353],[113.548467,22.215953],[113.547689,22.215933],[113.547137,22.215794],[113.547147,22.215442],[113.547877,22.214647],[113.548907,22.214503]]}}]}
